README.rst
setup.py
indiaDND/__init__.py
indiaDND/indiaDND.py
indiaDND.egg-info/PKG-INFO
indiaDND.egg-info/SOURCES.txt
indiaDND.egg-info/dependency_links.txt
indiaDND.egg-info/requires.txt
indiaDND.egg-info/top_level.txt